byteddatabus/__init__.py
byteddatabus/__main__.py
byteddatabus/main.py
bytedkafka_0.0.15-1.0.1.dist-info/LICENSE
bytedkafka_0.0.15-1.0.1.dist-info/METADATA
bytedkafka_0.0.15-1.0.1.dist-info/WHEEL
bytedkafka_0.0.15-1.0.1.dist-info/top_level.txt
bytedkafka_0.0.15-1.0.1.dist-info/RECORD
