Metadata-Version: 2.1
Name: bytedkafka-0.0.15
Version: 1.0.1
Summary: ByteDance Trace Package
Author: Danila Sashchenko
Author-email: danila.sashchenko@bytedance.com
Classifier: Programming Language :: Python :: 3
Classifier: License :: OSI Approved :: MIT License
Classifier: Operating System :: OS Independent
Requires-Python: >=3.2
License-File: LICENSE
